baidu_maps/__init__.py
baidu_maps/__main__.py
baidu_maps/map.py
baidu_maps-0.1.1.dist-info/licenses/LICENSE
baidu_maps-0.1.1.dist-info/METADATA
baidu_maps-0.1.1.dist-info/WHEEL
baidu_maps-0.1.1.dist-info/entry_points.txt
baidu_maps-0.1.1.dist-info/top_level.txt
baidu_maps-0.1.1.dist-info/RECORD
